{"stats":{"minecraft:killed_by":{"minecraft:drowned":1,"minecraft:skeleton":1},"minecraft:dropped":{"minecraft:wooden_axe":1},"minecraft:used":{"minecraft:oak_log":1,"minecraft:wooden_axe":5,"minecraft:sugar_cane":27,"minecraft:dirt":4,"minecraft:sand":3,"minecraft:crafting_table":1,"minecraft:egg":1,"minecraft:dandelion":6},"minecraft:custom":{"minecraft:time_since_rest":7611,"minecraft:sprint_one_cm":43368,"minecraft:damage_taken":730,"minecraft:walk_one_cm":43052,"minecraft:drop":1,"minecraft:damage_dealt":224,"minecraft:interact_with_crafting_table":1,"minecraft:fly_one_cm":54215,"minecraft:crouch_one_cm":278,"minecraft:play_time":41927,"minecraft:deaths":3,"minecraft:sneak_time":204,"minecraft:walk_under_water_one_cm":9913,"minecraft:jump":391,"minecraft:leave_game":6,"minecraft:walk_on_water_one_cm":8016,"minecraft:time_since_death":1274,"minecraft:total_world_time":41927,"minecraft:fall_one_cm":10959},"minecraft:picked_up":{"minecraft:dandelion":6,"minecraft:red_mushroom":1,"minecraft:sand":3,"minecraft:oak_log":2,"minecraft:spruce_log":3,"minecraft:dirt":4,"minecraft:sugar_cane":27,"minecraft:egg":1},"minecraft:crafted":{"minecraft:crafting_table":1,"minecraft:spruce_planks":12,"minecraft:stick":4,"minecraft:wooden_axe":2},"minecraft:mined":{"minecraft:large_fern":5,"minecraft:seagrass":1,"minecraft:spruce_log":3,"minecraft:dandelion":6,"minecraft:grass":1,"minecraft:grass_block":4,"minecraft:oak_log":2,"minecraft:sand":3,"minecraft:spruce_leaves":7,"minecraft:red_mushroom":1,"minecraft:sugar_cane":13,"minecraft:oak_leaves":2,"minecraft:fern":3}},"DataVersion":2730}